xcube_jl_ext/__init__.py
xcube_jl_ext/_version.py
xcube_jl_ext/config.py
xcube_jl_ext/handlers/__init__.py
xcube_jl_ext/handlers/labinfo.py
xcube_jl_ext/handlers/server.py
xcube_jl_ext/tests/__init__.py
xcube_jl_ext/tests/test_handlers.py
xcube_jl_ext-0.1.0.data/data/etc/jupyter/jupyter_notebook_config.d/xcube_jl_ext.json
xcube_jl_ext-0.1.0.data/data/etc/jupyter/jupyter_server_config.d/xcube_jl_ext.json
xcube_jl_ext-0.1.0.data/data/share/jupyter/labextensions/xcube-jl-ext/build_log.json
xcube_jl_ext-0.1.0.data/data/share/jupyter/labextensions/xcube-jl-ext/package.json
xcube_jl_ext-0.1.0.data/data/share/jupyter/labextensions/xcube-jl-ext/schemas/xcube-jl-ext/package.json.orig
xcube_jl_ext-0.1.0.data/data/share/jupyter/labextensions/xcube-jl-ext/schemas/xcube-jl-ext/plugin.json
xcube_jl_ext-0.1.0.data/data/share/jupyter/labextensions/xcube-jl-ext/static/c5d77a0aae1551c987e3970cb51544a8397f59d08e48605941c90379c2047117.png
xcube_jl_ext-0.1.0.data/data/share/jupyter/labextensions/xcube-jl-ext/static/lib_index_js.c30ba0ad3b001e727aea.js
xcube_jl_ext-0.1.0.data/data/share/jupyter/labextensions/xcube-jl-ext/static/lib_index_js.c30ba0ad3b001e727aea.js.map
xcube_jl_ext-0.1.0.data/data/share/jupyter/labextensions/xcube-jl-ext/static/remoteEntry.5439919631a0711b13cb.js
xcube_jl_ext-0.1.0.data/data/share/jupyter/labextensions/xcube-jl-ext/static/remoteEntry.5439919631a0711b13cb.js.map
xcube_jl_ext-0.1.0.data/data/share/jupyter/labextensions/xcube-jl-ext/static/style.js
xcube_jl_ext-0.1.0.data/data/share/jupyter/labextensions/xcube-jl-ext/static/style_index_js.07adf367c3d21f25c2be.js
xcube_jl_ext-0.1.0.data/data/share/jupyter/labextensions/xcube-jl-ext/static/style_index_js.07adf367c3d21f25c2be.js.map
xcube_jl_ext-0.1.0.data/data/share/jupyter/labextensions/xcube-jl-ext/static/vendors-node_modules_css-loader_dist_runtime_api_js-node_modules_css-loader_dist_runtime_cssW-7d5e6f.b0914c1152afc1e25ea2.js
xcube_jl_ext-0.1.0.dist-info/METADATA
xcube_jl_ext-0.1.0.dist-info/WHEEL
xcube_jl_ext-0.1.0.dist-info/licenses/LICENSE
xcube_jl_ext-0.1.0.dist-info/RECORD
