Metadata-Version: 2.1
Name: xcube_jl_ext
Version: 0.1.0
Summary: xcube JupyterLab integration
Project-URL: Homepage, https://github.com/dcs4cop/xcube-jl-ext
Project-URL: Bug Tracker, https://github.com/dcs4cop/xcube-jl-ext/issues
Project-URL: Repository, https://github.com/dcs4cop/xcube-jl-ext.git
Author-email: Norman Fomferra <norman.fomferra@brockmann-consult.de>
License: BSD 3-Clause License
License-File: LICENSE
Classifier: Framework :: Jupyter
Classifier: Framework :: Jupyter :: JupyterLab
Classifier: Framework :: Jupyter :: JupyterLab :: 3
Classifier: Framework :: Jupyter :: JupyterLab :: Extensions
Classifier: Framework :: Jupyter :: JupyterLab :: Extensions :: Prebuilt
Classifier: License :: OSI Approved :: BSD License
Classifier: Programming Language :: Python
Classifier: Programming Language :: Python :: 3
Classifier: Programming Language :: Python :: 3.7
Classifier: Programming Language :: Python :: 3.8
Classifier: Programming Language :: Python :: 3.9
Classifier: Programming Language :: Python :: 3.10
Classifier: Programming Language :: Python :: 3.11
Requires-Python: >=3.7
Requires-Dist: jupyter-server-proxy<4,>=3.2.0
Requires-Dist: jupyter-server<3,>=1.21
Provides-Extra: test
Requires-Dist: coverage; extra == 'test'
Requires-Dist: pytest; extra == 'test'
Requires-Dist: pytest-asyncio; extra == 'test'
Requires-Dist: pytest-cov; extra == 'test'
Requires-Dist: pytest-jupyter[server]>=0.6.0; extra == 'test'
